LICENCE
xdg/__init__.py
xdg/py.typed
xdg-5.1.0.dist-info/WHEEL
xdg-5.1.0.dist-info/METADATA
xdg-5.1.0.dist-info/RECORD
